KingWanhuiAiqingJihua/README.md
KingWanhuiAiqingJihua/__init__.py
KingWanhuiAiqingJihua/__main__.py
KingWanhuiAiqingJihua/file.epub
KingWanhuiAiqingJihua/index.html
KingWanhuiAiqingJihua/css/__init__.py
KingWanhuiAiqingJihua/css/annotations.css
KingWanhuiAiqingJihua/css/main.css
KingWanhuiAiqingJihua/css/normalize.css
KingWanhuiAiqingJihua/css/popup.css
KingWanhuiAiqingJihua/font/__init__.py
KingWanhuiAiqingJihua/font/fontello.eot
KingWanhuiAiqingJihua/font/fontello.svg
KingWanhuiAiqingJihua/font/fontello.ttf
KingWanhuiAiqingJihua/font/fontello.woff
KingWanhuiAiqingJihua/img/__init__.py
KingWanhuiAiqingJihua/img/annotator-glyph-sprite.png
KingWanhuiAiqingJihua/img/annotator-icon-sprite.png
KingWanhuiAiqingJihua/img/apple-touch-icon.png
KingWanhuiAiqingJihua/img/cancelfullscreen.png
KingWanhuiAiqingJihua/img/close.png
KingWanhuiAiqingJihua/img/fullscreen.png
KingWanhuiAiqingJihua/img/loader.gif
KingWanhuiAiqingJihua/img/menu-icon.png
KingWanhuiAiqingJihua/img/save.png
KingWanhuiAiqingJihua/img/saved.png
KingWanhuiAiqingJihua/img/settings-s.png
KingWanhuiAiqingJihua/img/settings.png
KingWanhuiAiqingJihua/img/star.png
KingWanhuiAiqingJihua/js/__init__.py
KingWanhuiAiqingJihua/js/epub.js
KingWanhuiAiqingJihua/js/epub.min.js
KingWanhuiAiqingJihua/js/epub.min.map
KingWanhuiAiqingJihua/js/hooks.min.js
KingWanhuiAiqingJihua/js/hooks.min.map
KingWanhuiAiqingJihua/js/reader.js
KingWanhuiAiqingJihua/js/reader.js.map
KingWanhuiAiqingJihua/js/reader.min.js
KingWanhuiAiqingJihua/js/reader.min.map
KingWanhuiAiqingJihua/js/hooks/__init__.py
KingWanhuiAiqingJihua/js/hooks/extensions/__init__.py
KingWanhuiAiqingJihua/js/hooks/extensions/highlight.js
KingWanhuiAiqingJihua/js/libs/__init__.py
KingWanhuiAiqingJihua/js/libs/jquery.min.js
KingWanhuiAiqingJihua/js/libs/localforage.min.js
KingWanhuiAiqingJihua/js/libs/screenfull.js
KingWanhuiAiqingJihua/js/libs/screenfull.min.js
KingWanhuiAiqingJihua/js/libs/zip.min.js
KingWanhuiAiqingJihua/js/plugins/__init__.py
king_wanhui_aiqing_jihua-2022.10.11.0.dist-info/METADATA
king_wanhui_aiqing_jihua-2022.10.11.0.dist-info/WHEEL
king_wanhui_aiqing_jihua-2022.10.11.0.dist-info/entry_points.txt
king_wanhui_aiqing_jihua-2022.10.11.0.dist-info/top_level.txt
king_wanhui_aiqing_jihua-2022.10.11.0.dist-info/RECORD
